<?xml version="1.0" encoding="UTF-8" standalone="yes"?><imgdir name="57411.img"><imgdir name="QuestInfo"><string name="name" value="敵の目を隠せ4"/><int name="area" value="58"/><string name="0" value="ケンシン公は私を敵兵に勘違いしたのか、いきなり切ろうとしていてちょっと驚いたが…まだ状況がよく分からないから経緯を話したほうが良さそうだ。"/><string name="1" value="戦場は戦闘を楽しむところであって挨拶をするところではないというケンシン公。彼女の戦闘本能が満たされるまで会話らしい会話をするのは難しそうだ。当初の目的どおり#r#o9421512##kを退治しよう。"/><string name="2" value="充分な戦闘を終えた後、ケンシン公とろくに会話をすることができるようになった。女性の身で軍神と呼ばれるくらいだから戦闘においては右に出る者がない。"/><string name="demandSummary" value="#o9421512# #a574111#
"/><string name="rewardSummary" value="#Wbasic#
#fUI/UIWindow2.img/QuestIcon/8/0# 1,555
&apos;越後の龍&apos; 퀘스트로 진행 가능"/></imgdir><imgdir name="Check"><imgdir name="0"><int name="npc" value="9130085"/><string name="startscript" value="q57411s"/><int name="lvmin" value="19"/><imgdir name="quest"><imgdir name="0"><int name="id" value="57410"/><int name="state" value="2"/></imgdir></imgdir><imgdir name="job"><int name="0" value="4200"/><int name="1" value="4210"/><int name="2" value="4211"/><int name="3" value="4212"/></imgdir></imgdir><imgdir name="1"><int name="npc" value="9130085"/><string name="endscript" value="q57411e"/><imgdir name="mob"><imgdir name="0"><int name="id" value="9421512"/><int name="count" value="50"/></imgdir></imgdir></imgdir></imgdir><imgdir name="Act"><imgdir name="0"></imgdir><imgdir name="1"></imgdir></imgdir><imgdir name="Say"><imgdir name="0"></imgdir><imgdir name="1"><imgdir name="stop"><imgdir name="default"><string name="0" value="まだ気がすまないようだ。こんな偵察兵なんて50名は軽く倒せるんじゃないか？"/><imgdir name="illustration"><imgdir name="0"><int name="faceIndex" value="1"/></imgdir></imgdir></imgdir></imgdir></imgdir></imgdir></imgdir>